MGSIM/CommTable.py
MGSIM/Genome_Download.py
MGSIM/SimComms.py
MGSIM/SimHtReads.py
MGSIM/SimReads.py
MGSIM/Utils.py
MGSIM/__init__.py
MGSIM/__main__.py
MGSIM/Commands/Communities.py
MGSIM/Commands/Genome_download.py
MGSIM/Commands/Genome_rename.py
MGSIM/Commands/HtReads.py
MGSIM/Commands/Reads.py
MGSIM/Commands/__init__.py
tests/__init__.py
tests/test_Communities.py
tests/test_Genome_download.py
tests/test_Genome_rename.py
tests/test_HtReads.py
tests/test_Reads.py
tests/test_Utils.py
MGSIM-0.2.7.dist-info/LICENSE
MGSIM-0.2.7.dist-info/METADATA
MGSIM-0.2.7.dist-info/WHEEL
MGSIM-0.2.7.dist-info/entry_points.txt
MGSIM-0.2.7.dist-info/top_level.txt
MGSIM-0.2.7.dist-info/RECORD
